[{"name":"Anna Regina","countryCode":"GY","stateCode":"PM","latitude":7.26439,"longitude":-58.50769},{"name":"Bartica","countryCode":"GY","stateCode":"CU","latitude":6.40799,"longitude":-58.62192},{"name":"Georgetown","countryCode":"GY","stateCode":"DE","latitude":6.80448,"longitude":-58.15527},{"name":"Lethem","countryCode":"GY","stateCode":"UT","latitude":3.38333,"longitude":-59.8},{"name":"Linden","countryCode":"GY","stateCode":"UD","latitude":6.00809,"longitude":-58.30714},{"name":"Mabaruma","countryCode":"GY","stateCode":"BA","latitude":8.2,"longitude":-59.78333},{"name":"Mahaica Village","countryCode":"GY","stateCode":"DE","latitude":6.68405,"longitude":-57.92181},{"name":"Mahaicony Village","countryCode":"GY","stateCode":"MA","latitude":6.57633,"longitude":-57.80486},{"name":"Mahdia","countryCode":"GY","stateCode":"PT","latitude":5.26667,"longitude":-59.15},{"name":"New Amsterdam","countryCode":"GY","stateCode":"EB","latitude":6.24793,"longitude":-57.5171},{"name":"Parika","countryCode":"GY","stateCode":"ES","latitude":6.83712,"longitude":-58.42941},{"name":"Rosignol","countryCode":"GY","stateCode":"MA","latitude":6.27095,"longitude":-57.53697},{"name":"Skeldon","countryCode":"GY","stateCode":"EB","latitude":5.88333,"longitude":-57.13333},{"name":"Vreed-en-Hoop","countryCode":"GY","stateCode":"ES","latitude":6.80927,"longitude":-58.19798}]
