[{"name":"‘Eilabun","countryCode":"IL","stateCode":"Z","latitude":32.83693,"longitude":35.40029},{"name":"‘En Boqeq","countryCode":"IL","stateCode":"D","latitude":31.19941,"longitude":35.36253},{"name":"‘Uzeir","countryCode":"IL","stateCode":"Z","latitude":32.79212,"longitude":35.32984},{"name":"Abū Ghaush","countryCode":"IL","stateCode":"JM","latitude":31.80592,"longitude":35.1093},{"name":"Acre","countryCode":"IL","stateCode":"Z","latitude":32.92814,"longitude":35.07647},{"name":"Afula","countryCode":"IL","stateCode":"Z","latitude":32.60907,"longitude":35.2892},{"name":"Arad","countryCode":"IL","stateCode":"D","latitude":31.25882,"longitude":35.21282},{"name":"Ashdod","countryCode":"IL","stateCode":"D","latitude":31.79213,"longitude":34.64966},{"name":"Ashkelon","countryCode":"IL","stateCode":"D","latitude":31.66926,"longitude":34.57149},{"name":"Atlit","countryCode":"IL","stateCode":"HA","latitude":32.68889,"longitude":34.94236},{"name":"Azor","countryCode":"IL","stateCode":"TA","latitude":32.0243,"longitude":34.80632},{"name":"Basmat Ṭab‘ūn","countryCode":"IL","stateCode":"Z","latitude":32.73898,"longitude":35.15716},{"name":"Bat Yam","countryCode":"IL","stateCode":"TA","latitude":32.02379,"longitude":34.75185},{"name":"Beersheba","countryCode":"IL","stateCode":"D","latitude":31.25181,"longitude":34.7913},{"name":"Beit Jann","countryCode":"IL","stateCode":"Z","latitude":32.96464,"longitude":35.38152},{"name":"Bet Dagan","countryCode":"IL","stateCode":"M","latitude":32.00191,"longitude":34.82977},{"name":"Bet She’an","countryCode":"IL","stateCode":"Z","latitude":32.49728,"longitude":35.49632},{"name":"Bet Shemesh","countryCode":"IL","stateCode":"JM","latitude":31.73072,"longitude":34.99293},{"name":"Bet Yiẕẖaq","countryCode":"IL","stateCode":"M","latitude":32.32751,"longitude":34.88878},{"name":"Bīr el Maksūr","countryCode":"IL","stateCode":"Z","latitude":32.77732,"longitude":35.22069},{"name":"Bnei Ayish","countryCode":"IL","stateCode":"M","latitude":31.78333,"longitude":34.75},{"name":"Bnei Brak","countryCode":"IL","stateCode":"TA","latitude":32.08074,"longitude":34.8338},{"name":"Bu‘eina","countryCode":"IL","stateCode":"Z","latitude":32.80636,"longitude":35.36486},{"name":"Buqei‘a","countryCode":"IL","stateCode":"Z","latitude":32.97747,"longitude":35.33345},{"name":"Caesarea","countryCode":"IL","stateCode":"HA","latitude":32.51888,"longitude":34.90459},{"name":"Dabbūrīya","countryCode":"IL","stateCode":"Z","latitude":32.69256,"longitude":35.37123},{"name":"Daliyat al Karmel","countryCode":"IL","stateCode":"HA","latitude":32.69383,"longitude":35.04686},{"name":"Deir Ḥannā","countryCode":"IL","stateCode":"Z","latitude":32.86196,"longitude":35.36365},{"name":"Dimona","countryCode":"IL","stateCode":"D","latitude":31.07079,"longitude":35.03269},{"name":"Eilat","countryCode":"IL","stateCode":"D","latitude":29.55805,"longitude":34.94821},{"name":"El Fureidīs","countryCode":"IL","stateCode":"HA","latitude":32.59812,"longitude":34.95153},{"name":"El Mazra‘a","countryCode":"IL","stateCode":"Z","latitude":32.98338,"longitude":35.09837},{"name":"Elyakhin","countryCode":"IL","stateCode":"M","latitude":32.40793,"longitude":34.92433},{"name":"Er Reina","countryCode":"IL","stateCode":"Z","latitude":32.72339,"longitude":35.31622},{"name":"Esh Sheikh Dannūn","countryCode":"IL","stateCode":"Z","latitude":32.9941,"longitude":35.14805},{"name":"Eṭ Ṭaiyiba","countryCode":"IL","stateCode":"M","latitude":32.26616,"longitude":35.00893},{"name":"Even Yehuda","countryCode":"IL","stateCode":"M","latitude":32.26959,"longitude":34.88759},{"name":"Gan Yavne","countryCode":"IL","stateCode":"M","latitude":31.78737,"longitude":34.70659},{"name":"Ganei Tikva","countryCode":"IL","stateCode":"M","latitude":32.05971,"longitude":34.8732},{"name":"Gedera","countryCode":"IL","stateCode":"M","latitude":31.81456,"longitude":34.77998},{"name":"Giv'at Shmuel","countryCode":"IL","stateCode":"TA","latitude":32.07817,"longitude":34.84858},{"name":"Givatayim","countryCode":"IL","stateCode":"TA","latitude":32.07225,"longitude":34.81253},{"name":"Hadera","countryCode":"IL","stateCode":"HA","latitude":32.44192,"longitude":34.9039},{"name":"Haifa","countryCode":"IL","stateCode":"HA","latitude":32.81841,"longitude":34.9885},{"name":"Har Adar","countryCode":"IL","stateCode":"JM","latitude":31.82754,"longitude":35.13093},{"name":"Herzliya","countryCode":"IL","stateCode":"TA","latitude":32.16627,"longitude":34.82536},{"name":"Herzliya Pituah","countryCode":"IL","stateCode":"TA","latitude":32.17409,"longitude":34.8028},{"name":"Hod HaSharon","countryCode":"IL","stateCode":"M","latitude":32.15934,"longitude":34.8932},{"name":"H̱olon","countryCode":"IL","stateCode":"TA","latitude":32.01034,"longitude":34.77918},{"name":"Ḥurfeish","countryCode":"IL","stateCode":"Z","latitude":33.01711,"longitude":35.34835},{"name":"Ibṭīn","countryCode":"IL","stateCode":"HA","latitude":32.7615,"longitude":35.11402},{"name":"Iksāl","countryCode":"IL","stateCode":"Z","latitude":32.68164,"longitude":35.32365},{"name":"Jaffa","countryCode":"IL","stateCode":"TA","latitude":32.05043,"longitude":34.75224},{"name":"Jaljūlya","countryCode":"IL","stateCode":"M","latitude":32.1547,"longitude":34.95372},{"name":"Jerusalem","countryCode":"IL","stateCode":"JM","latitude":31.76904,"longitude":35.21633},{"name":"Jīsh","countryCode":"IL","stateCode":"Z","latitude":33.02216,"longitude":35.44694},{"name":"Judeida Makr","countryCode":"IL","stateCode":"Z","latitude":32.9282,"longitude":35.15705},{"name":"Kābūl","countryCode":"IL","stateCode":"Z","latitude":32.86856,"longitude":35.21171},{"name":"Kafr Kammā","countryCode":"IL","stateCode":"Z","latitude":32.72129,"longitude":35.44122},{"name":"Kafr Kannā","countryCode":"IL","stateCode":"Z","latitude":32.7466,"longitude":35.34242},{"name":"Kafr Mandā","countryCode":"IL","stateCode":"Z","latitude":32.81034,"longitude":35.26009},{"name":"Kafr Miṣr","countryCode":"IL","stateCode":"Z","latitude":32.64521,"longitude":35.42147},{"name":"Kafr Qāsim","countryCode":"IL","stateCode":"M","latitude":32.11406,"longitude":34.97624},{"name":"Karmi’el","countryCode":"IL","stateCode":"Z","latitude":32.91708,"longitude":35.30501},{"name":"Kaukab Abū el Hījā","countryCode":"IL","stateCode":"Z","latitude":32.83155,"longitude":35.24848},{"name":"Kefar H̱abad","countryCode":"IL","stateCode":"M","latitude":31.98793,"longitude":34.8516},{"name":"Kefar Rosh HaNiqra","countryCode":"IL","stateCode":"Z","latitude":33.08607,"longitude":35.11348},{"name":"Kefar Shemaryahu","countryCode":"IL","stateCode":"TA","latitude":32.18529,"longitude":34.82082},{"name":"Kefar Tavor","countryCode":"IL","stateCode":"Z","latitude":32.68655,"longitude":35.42118},{"name":"Kefar Weradim","countryCode":"IL","stateCode":"Z","latitude":32.99385,"longitude":35.27793},{"name":"Kefar Yona","countryCode":"IL","stateCode":"M","latitude":32.31669,"longitude":34.93507},{"name":"Kfar Saba","countryCode":"IL","stateCode":"M","latitude":32.175,"longitude":34.90694},{"name":"Kfar Yasif","countryCode":"IL","stateCode":"Z","latitude":32.95451,"longitude":35.1623},{"name":"Lapid","countryCode":"IL","stateCode":"M","latitude":31.91764,"longitude":35.03222},{"name":"Lehavim","countryCode":"IL","stateCode":"D","latitude":31.37284,"longitude":34.81619},{"name":"Lod","countryCode":"IL","stateCode":"M","latitude":31.9467,"longitude":34.8903},{"name":"maalot Tarshīhā","countryCode":"IL","stateCode":"Z","latitude":33.01667,"longitude":35.26667},{"name":"Maghār","countryCode":"IL","stateCode":"Z","latitude":32.88984,"longitude":35.40703},{"name":"Mazkeret Batya","countryCode":"IL","stateCode":"M","latitude":31.85357,"longitude":34.84646},{"name":"Metulla","countryCode":"IL","stateCode":"Z","latitude":33.27918,"longitude":35.5795},{"name":"Mevasseret Ẕiyyon","countryCode":"IL","stateCode":"JM","latitude":31.80186,"longitude":35.15072},{"name":"Mi‘ilyā","countryCode":"IL","stateCode":"Z","latitude":33.02781,"longitude":35.25658},{"name":"Midreshet Ben-Gurion","countryCode":"IL","stateCode":"D","latitude":30.85154,"longitude":34.7834},{"name":"Migdal Ha‘Emeq","countryCode":"IL","stateCode":"Z","latitude":32.67597,"longitude":35.23986},{"name":"Mitzpe Ramon","countryCode":"IL","stateCode":"D","latitude":30.60944,"longitude":34.80111},{"name":"Modi‘in Makkabbim Re‘ut","countryCode":"IL","stateCode":"M","latitude":31.89385,"longitude":35.01504},{"name":"Modiin Ilit","countryCode":"IL","stateCode":"JM","latitude":31.93221,"longitude":35.04416},{"name":"Nahariyya","countryCode":"IL","stateCode":"Z","latitude":33.00892,"longitude":35.09814},{"name":"Naḥf","countryCode":"IL","stateCode":"Z","latitude":32.93444,"longitude":35.31679},{"name":"Nazareth","countryCode":"IL","stateCode":"Z","latitude":32.70056,"longitude":35.29722},{"name":"Nefat ‘Akko","countryCode":"IL","stateCode":"Z","latitude":32.95,"longitude":35.23333},{"name":"Neẖalim","countryCode":"IL","stateCode":"M","latitude":32.06012,"longitude":34.91069},{"name":"Nein","countryCode":"IL","stateCode":"Z","latitude":32.63063,"longitude":35.34885},{"name":"Nesher","countryCode":"IL","stateCode":"HA","latitude":32.76622,"longitude":35.04425},{"name":"Ness Ziona","countryCode":"IL","stateCode":"M","latitude":31.92933,"longitude":34.79868},{"name":"Netanya","countryCode":"IL","stateCode":"M","latitude":32.33291,"longitude":34.85992},{"name":"Netivot","countryCode":"IL","stateCode":"D","latitude":31.42305,"longitude":34.58911},{"name":"Nirit","countryCode":"IL","stateCode":"M","latitude":32.14677,"longitude":34.98622},{"name":"Nof Ayalon","countryCode":"IL","stateCode":"M","latitude":31.87111,"longitude":34.99081},{"name":"Nordiyya","countryCode":"IL","stateCode":"M","latitude":32.3147,"longitude":34.89617},{"name":"Ofaqim","countryCode":"IL","stateCode":"D","latitude":31.3141,"longitude":34.62025},{"name":"Or Yehuda","countryCode":"IL","stateCode":"TA","latitude":32.02923,"longitude":34.85788},{"name":"Pardesiyya","countryCode":"IL","stateCode":"M","latitude":32.30577,"longitude":34.90911},{"name":"Pasuta","countryCode":"IL","stateCode":"Z","latitude":33.04895,"longitude":35.30893},{"name":"Petaẖ Tiqwa","countryCode":"IL","stateCode":"M","latitude":32.08707,"longitude":34.88747},{"name":"Qalansuwa","countryCode":"IL","stateCode":"M","latitude":32.28493,"longitude":34.98106},{"name":"Qiryat Ata","countryCode":"IL","stateCode":"HA","latitude":32.81149,"longitude":35.11323},{"name":"Qiryat Bialik","countryCode":"IL","stateCode":"HA","latitude":32.8275,"longitude":35.08583},{"name":"Qiryat Gat","countryCode":"IL","stateCode":"D","latitude":31.60998,"longitude":34.76422},{"name":"Qiryat Moẕqin","countryCode":"IL","stateCode":"HA","latitude":32.83706,"longitude":35.0776},{"name":"Qiryat Shemona","countryCode":"IL","stateCode":"Z","latitude":33.20733,"longitude":35.57212},{"name":"Qiryat Yam","countryCode":"IL","stateCode":"HA","latitude":32.84966,"longitude":35.06973},{"name":"Ra'anana","countryCode":"IL","stateCode":"M","latitude":32.1836,"longitude":34.87386},{"name":"Rahat","countryCode":"IL","stateCode":"D","latitude":31.39547,"longitude":34.75699},{"name":"Ramat Gan","countryCode":"IL","stateCode":"TA","latitude":32.08227,"longitude":34.81065},{"name":"Ramat HaSharon","countryCode":"IL","stateCode":"TA","latitude":32.14613,"longitude":34.8394},{"name":"Ramat Yishay","countryCode":"IL","stateCode":"Z","latitude":32.70444,"longitude":35.1707},{"name":"Ramla","countryCode":"IL","stateCode":"M","latitude":31.92923,"longitude":34.86563},{"name":"Reẖovot","countryCode":"IL","stateCode":"M","latitude":31.89421,"longitude":34.81199},{"name":"Rekhasim","countryCode":"IL","stateCode":"HA","latitude":32.74907,"longitude":35.09901},{"name":"Rishon LeẔiyyon","countryCode":"IL","stateCode":"M","latitude":31.97102,"longitude":34.78939},{"name":"Rosh Ha‘Ayin","countryCode":"IL","stateCode":"M","latitude":32.09556,"longitude":34.95664},{"name":"Rosh Pinna","countryCode":"IL","stateCode":"Z","latitude":32.96894,"longitude":35.54258},{"name":"Rumat Heib","countryCode":"IL","stateCode":"Z","latitude":32.77802,"longitude":35.30571},{"name":"Safed","countryCode":"IL","stateCode":"Z","latitude":32.96465,"longitude":35.496},{"name":"Sājūr","countryCode":"IL","stateCode":"Z","latitude":32.94266,"longitude":35.34136},{"name":"Sakhnīn","countryCode":"IL","stateCode":"Z","latitude":32.86422,"longitude":35.29707},{"name":"Sallama","countryCode":"IL","stateCode":"Z","latitude":32.89443,"longitude":35.36931},{"name":"Savyon","countryCode":"IL","stateCode":"M","latitude":32.04966,"longitude":34.8777},{"name":"Sederot","countryCode":"IL","stateCode":"D","latitude":31.525,"longitude":34.59693},{"name":"Shelomi","countryCode":"IL","stateCode":"Z","latitude":33.07216,"longitude":35.14452},{"name":"Shibli","countryCode":"IL","stateCode":"Z","latitude":32.69464,"longitude":35.39252},{"name":"Shoham","countryCode":"IL","stateCode":"M","latitude":31.99866,"longitude":34.94559},{"name":"Sūlam","countryCode":"IL","stateCode":"Z","latitude":32.60606,"longitude":35.33408},{"name":"Tamra","countryCode":"IL","stateCode":"Z","latitude":32.85301,"longitude":35.1987},{"name":"Tel Aviv","countryCode":"IL","stateCode":"TA","latitude":32.08088,"longitude":34.78057},{"name":"Tel Mond","countryCode":"IL","stateCode":"M","latitude":32.24995,"longitude":34.91737},{"name":"Tiberias","countryCode":"IL","stateCode":"Z","latitude":32.79221,"longitude":35.53124},{"name":"Timrat","countryCode":"IL","stateCode":"Z","latitude":32.70302,"longitude":35.22359},{"name":"Tirah","countryCode":"IL","stateCode":"M","latitude":32.2341,"longitude":34.95023},{"name":"Tirat Karmel","countryCode":"IL","stateCode":"HA","latitude":32.76021,"longitude":34.97183},{"name":"Umm el Faḥm","countryCode":"IL","stateCode":"HA","latitude":32.51725,"longitude":35.15349},{"name":"West Jerusalem","countryCode":"IL","stateCode":"JM","latitude":31.78199,"longitude":35.21961},{"name":"Yavné","countryCode":"IL","stateCode":"M","latitude":31.87808,"longitude":34.73983},{"name":"Yavne’el","countryCode":"IL","stateCode":"Z","latitude":32.70619,"longitude":35.50435},{"name":"Yehud","countryCode":"IL","stateCode":"M","latitude":32.03317,"longitude":34.89091},{"name":"Yehud-Monosson","countryCode":"IL","stateCode":"TA","latitude":32.0284,"longitude":34.8796},{"name":"Yeroẖam","countryCode":"IL","stateCode":"D","latitude":30.98822,"longitude":34.93176},{"name":"Ẕur Hadassa","countryCode":"IL","stateCode":"JM","latitude":31.71912,"longitude":35.09708},{"name":"Ẕur Moshe","countryCode":"IL","stateCode":"M","latitude":32.29819,"longitude":34.91313}]
