[{"name":"Afega","countryCode":"WS","stateCode":"TU","latitude":-13.79726,"longitude":-171.85308},{"name":"Apia","countryCode":"WS","stateCode":"TU","latitude":-13.83333,"longitude":-171.76666},{"name":"Asau","countryCode":"WS","stateCode":"VS","latitude":-13.51963,"longitude":-172.63784},{"name":"Falefa","countryCode":"WS","stateCode":"AT","latitude":-13.88695,"longitude":-171.58805},{"name":"Fasito‘outa","countryCode":"WS","stateCode":"AA","latitude":-13.81163,"longitude":-171.94063},{"name":"Gataivai","countryCode":"WS","stateCode":"PA","latitude":-13.7736,"longitude":-172.38802},{"name":"Leulumoega","countryCode":"WS","stateCode":"AA","latitude":-13.82297,"longitude":-171.96127},{"name":"Lotofagā","countryCode":"WS","stateCode":"AT","latitude":-13.97643,"longitude":-171.85781},{"name":"Lufilufi","countryCode":"WS","stateCode":"AT","latitude":-13.87449,"longitude":-171.59857},{"name":"Malie","countryCode":"WS","stateCode":"TU","latitude":-13.80044,"longitude":-171.8469},{"name":"Matavai","countryCode":"WS","stateCode":"GI","latitude":-14.03208,"longitude":-171.64768},{"name":"Mulifanua","countryCode":"WS","stateCode":"AL","latitude":-13.83183,"longitude":-172.03602},{"name":"Nofoali‘i","countryCode":"WS","stateCode":"AA","latitude":-13.8217,"longitude":-171.95873},{"name":"Safotu","countryCode":"WS","stateCode":"GI","latitude":-13.45132,"longitude":-172.40177},{"name":"Samamea","countryCode":"WS","stateCode":"VF","latitude":-13.93375,"longitude":-171.53122},{"name":"Satapuala","countryCode":"WS","stateCode":"AA","latitude":-13.83535,"longitude":-171.97963},{"name":"Solosolo","countryCode":"WS","stateCode":"AT","latitude":-13.87504,"longitude":-171.64181},{"name":"Vailima","countryCode":"WS","stateCode":"TU","latitude":-13.86417,"longitude":-171.76126},{"name":"Vailoa","countryCode":"WS","stateCode":"PA","latitude":-13.75551,"longitude":-172.30698},{"name":"Vaiusu","countryCode":"WS","stateCode":"TU","latitude":-13.82678,"longitude":-171.79333}]
